data_id/abcs.py
data_id/api.py
data_id/cli.py
data_id/data_scanners.py
data_id/results_database.py
data_id/schema_scanners.py
data_id/utils.py
data_id-0.0.1.dist-info/entry_points.txt
data_id-0.0.1.dist-info/LICENSE
data_id-0.0.1.dist-info/WHEEL
data_id-0.0.1.dist-info/METADATA
data_id-0.0.1.dist-info/RECORD
